odoo/addons/l10n_br_website_sale_delivery/README.rst
odoo/addons/l10n_br_website_sale_delivery/__init__.py
odoo/addons/l10n_br_website_sale_delivery/__manifest__.py
odoo/addons/l10n_br_website_sale_delivery/controllers/__init__.py
odoo/addons/l10n_br_website_sale_delivery/controllers/main.py
odoo/addons/l10n_br_website_sale_delivery/i18n/l10n_br_website_sale_delivery.pot
odoo/addons/l10n_br_website_sale_delivery/i18n/pt_BR.po
odoo/addons/l10n_br_website_sale_delivery/readme/CONFIGURE.rst
odoo/addons/l10n_br_website_sale_delivery/readme/CONTRIBUTORS.rst
odoo/addons/l10n_br_website_sale_delivery/readme/DESCRIPTION.rst
odoo/addons/l10n_br_website_sale_delivery/readme/HISTORY.rst
odoo/addons/l10n_br_website_sale_delivery/readme/INSTALL.rst
odoo/addons/l10n_br_website_sale_delivery/readme/ROADMAP.rst
odoo/addons/l10n_br_website_sale_delivery/readme/USAGE.rst
odoo/addons/l10n_br_website_sale_delivery/static/description/icon.png
odoo/addons/l10n_br_website_sale_delivery/static/description/index.html
odoo/addons/l10n_br_website_sale_delivery/static/src/js/l10n_br_website_sale_delivery_tour.js
odoo/addons/l10n_br_website_sale_delivery/tests/__init__.py
odoo/addons/l10n_br_website_sale_delivery/tests/test_website_sale_tour.py
odoo/addons/l10n_br_website_sale_delivery/views/assets.xml
odoo/addons/l10n_br_website_sale_delivery/views/website_sale_delivery_templates.xml
odoo12_addon_l10n_br_website_sale_delivery-12.0.2.1.0.dist-info/METADATA
odoo12_addon_l10n_br_website_sale_delivery-12.0.2.1.0.dist-info/WHEEL
odoo12_addon_l10n_br_website_sale_delivery-12.0.2.1.0.dist-info/top_level.txt
odoo12_addon_l10n_br_website_sale_delivery-12.0.2.1.0.dist-info/RECORD
