Metadata-Version: 2.1
Name: odoo12-addon-l10n-br-website-sale-delivery
Version: 12.0.2.1.0
Summary: Implements Brazilian freight values for delivery.
Home-page: https://github.com/oca/l10n-brazil
Author: KMEE,Odoo Community Association (OCA)
Author-email: support@odoo-community.org
License: AGPL-3
Platform: UNKNOWN
Classifier: Programming Language :: Python
Classifier: Framework :: Odoo
Classifier: License :: OSI Approved :: GNU Affero General Public License v3
Classifier: Development Status :: 3 - Alpha
Requires-Python: >=3.5
Requires-Dist: odoo12-addon-l10n-br-delivery
Requires-Dist: odoo12-addon-l10n-br-website-sale
Requires-Dist: odoo (<12.1dev,>=12.0a)
